fastani/__init__.py
fastani/config.py
fastani/fastani.py
fastani/logger.py
fastani/model.py
fastani/process.py
fastani/util.py
fastani/version.py
test/__init__.py
test/test_fastani.py
test/test_model.py
test/test_util.py
test/test_version.py
fastani-1.1.0.dist-info/LICENSE
fastani-1.1.0.dist-info/METADATA
fastani-1.1.0.dist-info/WHEEL
fastani-1.1.0.dist-info/top_level.txt
fastani-1.1.0.dist-info/RECORD
