Metadata-Version: 2.1
Name: fastani
Version: 1.1.0
Summary: A wrapper to the FastANI program.
Home-page: https://github.com/aaronmussig/FastANI
Author: Aaron Mussig
Author-email: aaronmussig@gmail.com
License: GNU AGPLv3
Project-URL: Bug Tracker, https://github.com/aaronmussig/FastANI
Project-URL: Documentation, https://github.com/aaronmussig/FastANI
Project-URL: Source Code, https://github.com/aaronmussig/FastANI
Platform: UNKNOWN
Classifier: Development Status :: 4 - Beta
Classifier: Intended Audience :: Developers
Classifier: License :: OSI Approved :: GNU Affero General Public License v3
Classifier: Natural Language :: English
Classifier: Operating System :: OS Independent
Classifier: Programming Language :: Python :: 3.6
Classifier: Topic :: Software Development
Classifier: Topic :: Scientific/Engineering :: Bio-Informatics
Requires-Python: >=3.6
License-File: LICENSE
Requires-Dist: tqdm
